delnx/__init__.py
delnx/_constants.py
delnx/_logging.py
delnx/_typing.py
delnx/_utils/__init__.py
delnx/ds/__init__.py
delnx/ds/_gmt.py
delnx/ds/_synthetic.py
delnx/models/__init__.py
delnx/models/_models.py
delnx/models/_utils.py
delnx/pl/__init__.py
delnx/pl/_baseplot.py
delnx/pl/_dotplot.py
delnx/pl/_filtered_genes.py
delnx/pl/_gseaplot.py
delnx/pl/_heatmapplot.py
delnx/pl/_matrixplot.py
delnx/pl/_palettes.py
delnx/pl/_violinplot.py
delnx/pl/_volcanoplot.py
delnx/pp/__init__.py
delnx/pp/_aucell.py
delnx/pp/_dispersion.py
delnx/pp/_filter_genes.py
delnx/pp/_get_de_genes.py
delnx/pp/_label_de_genes.py
delnx/pp/_pseudobulk.py
delnx/pp/_size_factors.py
delnx/pp/_utils.py
delnx/tl/__init__.py
delnx/tl/_de.py
delnx/tl/_de_tests.py
delnx/tl/_effects.py
delnx/tl/_gsea.py
delnx/tl/_jax_tests.py
delnx/tl/_utils.py
delnx-0.2.3.dist-info/METADATA
delnx-0.2.3.dist-info/WHEEL
delnx-0.2.3.dist-info/licenses/LICENSE
delnx-0.2.3.dist-info/RECORD
