Metadata-Version: 2.4
Name: delnx
Version: 0.2.3
Summary: Differential expression analysis for single-cell genomics
Project-URL: Documentation, https://delnx.readthedocs.io/
Project-URL: Homepage, https://github.com/joschif/delnx
Project-URL: Source, https://github.com/joschif/delnx
Author: Jonas Simon Fleck
Maintainer-email: Jonas Simon Fleck <jonas.simon.fleck@gmail.com>
License: 
License-File: LICENSE
Classifier: Programming Language :: Python :: 3 :: Only
Classifier: Programming Language :: Python :: 3.11
Classifier: Programming Language :: Python :: 3.12
Classifier: Programming Language :: Python :: 3.13
Requires-Python: >=3.11
Requires-Dist: adjusttext>=1.3
Requires-Dist: anndata>=0.12.0rc3
Requires-Dist: decoupler>=2
Requires-Dist: gseapy>=1.1.9
Requires-Dist: jax>=0.5.3
Requires-Dist: marsilea>=0.5.3
Requires-Dist: numpy>=2.0.2
Requires-Dist: pandas>=2.2.3
Requires-Dist: pydeseq2>=0.5
Requires-Dist: pynndescent>=0.5
Requires-Dist: rich>=14
Requires-Dist: scanpy>=1.11.2
Requires-Dist: scikit-learn>=1.5.1
Requires-Dist: scipy<1.16,>=1.15.3
Requires-Dist: session-info2>=0.1.2
Requires-Dist: statsmodels>=0.14.4
Requires-Dist: tqdm>=4.67.1
Provides-Extra: dev
Requires-Dist: hatch>=1.14.1; extra == 'dev'
Requires-Dist: myst-nb; extra == 'dev'
Requires-Dist: pre-commit>=4.2; extra == 'dev'
Requires-Dist: tox>=4; extra == 'dev'
Requires-Dist: twine>=4.0.2; extra == 'dev'
Provides-Extra: docs
Requires-Dist: docutils!=0.18.*,!=0.19.*,>=0.8; extra == 'docs'
Requires-Dist: furo; extra == 'docs'
Requires-Dist: ipykernel; extra == 'docs'
Requires-Dist: ipython; extra == 'docs'
Requires-Dist: jax; extra == 'docs'
Requires-Dist: myst-nb>=1.1; extra == 'docs'
Requires-Dist: pandas; extra == 'docs'
Requires-Dist: scvi-tools; extra == 'docs'
Requires-Dist: setuptools; extra == 'docs'
Requires-Dist: sphinx-autodoc-typehints; extra == 'docs'
Requires-Dist: sphinx-book-theme>=1; extra == 'docs'
Requires-Dist: sphinx-copybutton; extra == 'docs'
Requires-Dist: sphinx-design; extra == 'docs'
Requires-Dist: sphinx-tippy; extra == 'docs'
Requires-Dist: sphinx>=8; extra == 'docs'
Requires-Dist: sphinxcontrib-bibtex; extra == 'docs'
Requires-Dist: sphinxcontrib-bibtex>=2; extra == 'docs'
Requires-Dist: sphinxext-opengraph; extra == 'docs'
Requires-Dist: statsmodels; extra == 'docs'
Requires-Dist: tox>=4; extra == 'docs'
Requires-Dist: twine>=4.0.2; extra == 'docs'
Provides-Extra: test
Requires-Dist: coverage[toml]>=7; extra == 'test'
Requires-Dist: hatch>=1.14.1; extra == 'test'
Requires-Dist: pytest-cov>=6.1; extra == 'test'
Requires-Dist: pytest-mock>=3.14; extra == 'test'
Requires-Dist: pytest>=8.3.5; extra == 'test'
